dataset_handling/__init__.py
dataset_handling/dataloader.py
dataset_handling_ChrisPrein-1.0.1.dist-info/LICENSE
dataset_handling_ChrisPrein-1.0.1.dist-info/METADATA
dataset_handling_ChrisPrein-1.0.1.dist-info/WHEEL
dataset_handling_ChrisPrein-1.0.1.dist-info/top_level.txt
dataset_handling_ChrisPrein-1.0.1.dist-info/RECORD
