Metadata-Version: 2.1
Name: dataset-handling-ChrisPrein
Version: 1.0.1
Summary: A package for loading data from different sources and retrieving samples.
Home-page: https://github.com/ChrisPrein/dataset-handling
Author: ChrisPrein
Author-email: e01529038@student.tuwien.ac.at
Project-URL: Bug Tracker, https://github.com/ChrisPrein/dataset-handling/issues
Classifier: Programming Language :: Python :: 3
Classifier: License :: OSI Approved :: MIT License
Classifier: Operating System :: OS Independent
Requires-Python: >=3.6
License-File: LICENSE
